pyiltags/__init__.py
pyiltags/base.py
pyiltags/io.py
pyiltags/standard.py
pyiltags/util.py
pyiltags-0.1.1.dist-info/LICENSE
pyiltags-0.1.1.dist-info/METADATA
pyiltags-0.1.1.dist-info/WHEEL
pyiltags-0.1.1.dist-info/top_level.txt
pyiltags-0.1.1.dist-info/RECORD
