Metadata-Version: 2.1
Name: pyiltags
Version: 0.1.1
Summary: Pure Python implementation of InterlockLedger ILTags standard
Home-page: https://github.com/interlockledger/pyiltags
Author: InterlockLedger Network
Author-email: fchino@il2.io
Project-URL: Bug Tracker, https://github.com/interlockledger/pyiltags/issues
Classifier: Programming Language :: Python :: 3
Classifier: License :: OSI Approved :: MIT License
Classifier: Operating System :: OS Independent
Requires-Python: >=3.7
License-File: LICENSE
Requires-Dist: pyilint (>=0.2.2)
